ivutils/__init__.py
ivutils/cli.py
ivutils/file.py
ivutils/image.py
ivutils/video.py
ivutils/parsers/__init__.py
ivutils/parsers/parser_img.py
ivutils/parsers/parser_vid.py
ivutils-0.0.7.dist-info/licenses/LICENSE
ivutils-0.0.7.dist-info/METADATA
ivutils-0.0.7.dist-info/WHEEL
ivutils-0.0.7.dist-info/entry_points.txt
ivutils-0.0.7.dist-info/top_level.txt
ivutils-0.0.7.dist-info/RECORD
