Metadata-Version: 2.4
Name: ivutils
Version: 0.0.7
Home-page: https://github.com/thasan01/ivutils
License: MIT license
Keywords: computer-vision,opencv,image-processing,video-processing,imaging,utilities,transformation,automation,task
License-File: LICENSE
Requires-Dist: opencv-python~=4.10.0.84
Requires-Dist: numpy<2.1,>=1.22
Requires-Dist: pillow~=11.0.0
Requires-Dist: PyYAML~=6.0.3
Dynamic: description
Dynamic: description-content-type
Dynamic: home-page
Dynamic: keywords
Dynamic: license
Dynamic: license-file
Dynamic: requires-dist
